COPYING.md
MANIFEST.in
README.md
RELEASE-VERSION
setup.py
test.py
version.py
changes/ChangeLog-0.1.1.md
changes/ChangeLog-0.1.2.md
changes/ChangeLog-0.2.md
changes/ChangeLog-0.3.md
changes/ChangeLog-0.4.1.md
changes/ChangeLog-0.4.2.md
changes/ChangeLog-0.4.md
etc/lispd/ddt_root
etc/lispd/settings.py
pylisp/__init__.py
pylisp.egg-info/PKG-INFO
pylisp.egg-info/SOURCES.txt
pylisp.egg-info/dependency_links.txt
pylisp.egg-info/requires.txt
pylisp.egg-info/top_level.txt
pylisp/application/__init__.py
pylisp/application/lispd/__init__.py
pylisp/application/lispd/ddt_handler.py
pylisp/application/lispd/etr_handler.py
pylisp/application/lispd/map_server_registration.py
pylisp/application/lispd/message_handler.py
pylisp/application/lispd/received_message.py
pylisp/application/lispd/send_message.py
pylisp/application/lispd/settings.py
pylisp/application/lispd/address_tree/__init__.py
pylisp/application/lispd/address_tree/authoritative_container_node.py
pylisp/application/lispd/address_tree/base.py
pylisp/application/lispd/address_tree/container_node.py
pylisp/application/lispd/address_tree/ddt_referral_node.py
pylisp/application/lispd/address_tree/drop_node.py
pylisp/application/lispd/address_tree/etr_node.py
pylisp/application/lispd/address_tree/natively_forward_node.py
pylisp/application/lispd/utils/__init__.py
pylisp/application/lispd/utils/ddt_root_loader.py
pylisp/application/lispd/utils/prefix.py
pylisp/packet/__init__.py
pylisp/packet/ip/__init__.py
pylisp/packet/ip/ipv4.py
pylisp/packet/ip/protocol.py
pylisp/packet/ip/protocol_registry.py
pylisp/packet/ip/udp.py
pylisp/packet/ip/ipv6/__init__.py
pylisp/packet/ip/ipv6/base.py
pylisp/packet/ip/ipv6/destination_options_header.py
pylisp/packet/ip/ipv6/fragment_header.py
pylisp/packet/ip/ipv6/hop_by_hop_options_header.py
pylisp/packet/ip/ipv6/no_next_header.py
pylisp/packet/ip/ipv6/routing_header.py
pylisp/packet/lisp/__init__.py
pylisp/packet/lisp/data.py
pylisp/packet/lisp/control/__init__.py
pylisp/packet/lisp/control/base.py
pylisp/packet/lisp/control/constants.py
pylisp/packet/lisp/control/encapsulated_control_message.py
