Metadata-Version: 1.0
Name: pylisp
Version: 0.4.2
Summary: Locator/ID Separation Protocol (LISP) library
Home-page: https://github.com/steffann/pylisp
Author: S.J.M. Steffann
Author-email: sander@steffann.nl
License: BSD License
Keywords: lisp ddt
Platform: UNKNOWN
Classifier: Development Status :: 2 - Pre-Alpha
Classifier: Environment :: Console
Classifier: Intended Audience :: Developers
Classifier: Intended Audience :: Information Technology
Classifier: Intended Audience :: System Administrators
Classifier: License :: OSI Approved :: BSD License
Classifier: Natural Language :: English
Classifier: Operating System :: OS Independent
Classifier: Programming Language :: Python
Classifier: Topic :: Communications
Classifier: Topic :: Internet
Classifier: Topic :: Software Development :: Libraries
Classifier: Topic :: System :: Networking
Classifier: Topic :: Utilities
